LICENSE
MANIFEST.in
README.rst
helga_giphy.py
requirements.txt
setup.py
helga_giphy.egg-info/PKG-INFO
helga_giphy.egg-info/SOURCES.txt
helga_giphy.egg-info/dependency_links.txt
helga_giphy.egg-info/entry_points.txt
helga_giphy.egg-info/requires.txt
helga_giphy.egg-info/top_level.txt
helga_giphy.egg-info/zip-safe